{
  "directed": true,
  "multigraph": false,
  "graph": {},
  "nodes": [
    {
      "skill": "planner",
      "inputs": [
        "USER_QUERY"
      ],
      "metadata": {},
      "status": "complete",
      "result": {
        "success": true,
        "agent_name": "planner",
        "output": {
          "rationale": "The user request is a simple greeting which does not require external research or retrieval.",
          "nodes": [
            {
              "skill": "formatter",
              "inputs": [
                "USER_QUERY"
              ],
              "metadata": {
                "label": "out"
              }
            }
          ]
        },
        "artifacts": [],
        "successors": [
          {
            "skill": "formatter",
            "inputs": [
              "USER_QUERY"
            ],
            "metadata": {
              "label": "out"
            }
          }
        ],
        "cost": 0.0,
        "elapsed_s": 4.186046123504639,
        "provider": "gemini",
        "error": null
      },
      "_result_typed": true,
      "id": "n:1"
    },
    {
      "skill": "formatter",
      "inputs": [
        "USER_QUERY"
      ],
      "metadata": {
        "label": "out"
      },
      "status": "complete",
      "result": {
        "success": true,
        "agent_name": "formatter",
        "output": {
          "final_answer": "Hello, it is a pleasure to assist you today."
        },
        "artifacts": [],
        "successors": [],
        "cost": 0.0,
        "elapsed_s": 4.402621746063232,
        "provider": "gemini",
        "error": null
      },
      "_result_typed": true,
      "id": "n:2"
    }
  ],
  "edges": []
}