{
  "directed": true,
  "multigraph": false,
  "graph": {},
  "nodes": [
    {
      "skill": "planner",
      "inputs": [
        "USER_QUERY"
      ],
      "metadata": {},
      "status": "complete",
      "result": {
        "success": true,
        "agent_name": "planner",
        "output": {
          "rationale": "The memory hits do not contain information about Mysore localities, so I must use the researcher to find suitable residential areas for a non-Kannadiga.",
          "nodes": [
            {
              "skill": "researcher",
              "inputs": [
                "USER_QUERY"
              ],
              "metadata": {
                "label": "search_mysore",
                "question": "Which localities in Mysore are suitable for a non-Kannadiga to reside in?"
              }
            },
            {
              "skill": "formatter",
              "inputs": [
                "n:search_mysore"
              ],
              "metadata": {
                "label": "final_answer"
              }
            }
          ]
        },
        "artifacts": [],
        "successors": [
          {
            "skill": "researcher",
            "inputs": [
              "USER_QUERY"
            ],
            "metadata": {
              "label": "search_mysore",
              "question": "Which localities in Mysore are suitable for a non-Kannadiga to reside in?"
            }
          },
          {
            "skill": "formatter",
            "inputs": [
              "n:search_mysore"
            ],
            "metadata": {
              "label": "final_answer"
            }
          }
        ],
        "cost": 0.0,
        "elapsed_s": 3.8646841049194336,
        "provider": "gemini",
        "error": null
      },
      "_result_typed": true,
      "id": "n:1"
    },
    {
      "skill": "researcher",
      "inputs": [
        "USER_QUERY"
      ],
      "metadata": {
        "label": "search_mysore",
        "question": "Which localities in Mysore are suitable for a non-Kannadiga to reside in?"
      },
      "status": "complete",
      "result": {
        "success": true,
        "agent_name": "researcher",
        "output": {
          "question": "which locality in mysore is suitable for residence for a non kannadiga",
          "sources": [
            {
              "url": "https://mygate.com/blog/neighbourhood/best-residential-areas-in-mysore/",
              "title": "Top 7 best residential areas in Mysuru [Updated]"
            },
            {
              "url": "https://www.quora.com/What-are-the-best-residential-areas-in-Mysore",
              "title": "What are the best residential areas in Mysore?"
            }
          ],
          "findings": "Mysore (Mysuru) is generally considered a welcoming and cosmopolitan city due to its status as an educational hub, tourism center, and the presence of major IT companies like Infosys and Wipro. These factors attract a diverse population, making most developed localities suitable for non-Kannadigas.\n\nGokulam is often cited as one of the most upscale, cosmopolitan, and desirable neighborhoods, popular among expats and visitors due to its vibrant culture, yoga centers, and cafes. JP Nagar is another affluent, well-planned area that houses many prominent figures and offers a high quality of life.\n\nFor families seeking established infrastructure and greenery, Kuvempunagar is highly recommended for its well-maintained parks, wide roads, and proximity to essential services like hospitals and schools. Dattagalli and Bogadi are also noted for their well-developed residential environments and good connectivity, offering a mix of affordable and premium housing options.\n\nNewer, rapidly developing areas like Vijayanagar (4th Stage) and the industrial-residential zone of Hebbal are suitable for those looking for proximity to employment hubs and modern amenities at potentially competitive price points. Overall, because Mysore is a relatively compact and peaceful city, most major residential layouts are inclusive and well-integrated."
        },
        "artifacts": [],
        "successors": [],
        "cost": 0.0,
        "elapsed_s": 13.222444534301758,
        "provider": "gemini",
        "error": null
      },
      "_result_typed": true,
      "id": "n:2"
    },
    {
      "skill": "formatter",
      "inputs": [
        "n:2"
      ],
      "metadata": {
        "label": "final_answer"
      },
      "status": "complete",
      "result": {
        "success": true,
        "agent_name": "formatter",
        "output": {
          "final_answer": "Mysore is a welcoming and cosmopolitan city, making it highly suitable for non-Kannadigas. Because of its status as an educational and IT hub, most developed localities are inclusive and well-integrated. Recommended areas include: \n\n1. Gokulam: Highly cosmopolitan and popular among expats and visitors, known for its vibrant cafe culture and yoga centers.\n2. JP Nagar: An affluent, well-planned neighborhood offering a high quality of life.\n3. Kuvempunagar: Ideal for families, featuring established infrastructure, greenery, wide roads, and proximity to schools and hospitals.\n4. Dattagalli and Bogadi: Well-developed residential areas with good connectivity and a mix of housing options.\n5. Vijayanagar (4th Stage) and Hebbal: Suitable for those seeking modern amenities and proximity to employment hubs.\n\nSources: https://mygate.com/blog/neighbourhood/best-residential-areas-in-mysore/, https://www.quora.com/What-are-the-best-residential-areas-in-Mysore"
        },
        "artifacts": [],
        "successors": [],
        "cost": 0.0,
        "elapsed_s": 3.3204610347747803,
        "provider": "gemini",
        "error": null
      },
      "_result_typed": true,
      "id": "n:3"
    }
  ],
  "edges": [
    {
      "source": "n:2",
      "target": "n:3"
    }
  ]
}